class_inspector/__init__.py
class_inspector/_logger.py
class_inspector/create_tests.py
class_inspector/cst_walkers.py
class_inspector/custom_validators.py
class_inspector/data_structures.py
class_inspector/guard_conditions.py
class_inspector/transform.py
class_inspector/utils.py
class_inspector-0.3.1.dist-info/LICENSE
class_inspector-0.3.1.dist-info/METADATA
class_inspector-0.3.1.dist-info/WHEEL
class_inspector-0.3.1.dist-info/top_level.txt
class_inspector-0.3.1.dist-info/RECORD
