Metadata-Version: 2.2
Name: class_inspector
Version: 0.3.1
Summary: class inspector package
Author: Ed Cuss
Classifier: Programming Language :: Python :: 3
Classifier: License :: OSI Approved :: MIT License
Classifier: Operating System :: OS Independent
Requires-Python: >=3.9
License-File: LICENSE
Requires-Dist: attrs>=22.2.0
Requires-Dist: libcst<2,>=1.5.1
Requires-Dist: python-dotenv>=0.20.0
Requires-Dist: black>=24
Requires-Dist: isort>=5
Provides-Extra: test
Requires-Dist: numpy>=1.19.5; extra == "test"
Requires-Dist: pandas; extra == "test"
Requires-Dist: pytest; extra == "test"
Requires-Dist: pytest-cov; extra == "test"
Requires-Dist: hypothesis; extra == "test"
Requires-Dist: pre-commit; extra == "test"
Requires-Dist: tox; extra == "test"
Provides-Extra: lint
Requires-Dist: ruff; extra == "lint"
Requires-Dist: pylint>=3.0.1; extra == "lint"
Provides-Extra: docs
Requires-Dist: sphinx; extra == "docs"
Provides-Extra: dev
Requires-Dist: class_inspector[docs,lint,test]; extra == "dev"
